[{"name": "gap", "value": "43275"}, {"name": "Hanging", "value": "24610"}, {"name": "gas", "value": "19161"}, {"name": "sick", "value": "17120"}, {"name": "percent", "value": "16908"}, {"name": "spanks", "value": "15474"}, {"name": "dance", "value": "15197"}, {"name": "ive", "value": "15020"}, {"name": "getting", "value": "14871"}, {"name": "leader", "value": "14142"}, {"name": "gettin", "value": "13768"}, {"name": "alone", "value": "13078"}, {"name": "needwant", "value": "11847"}, {"name": "knot", "value": "11028"}, {"name": "know", "value": "10458"}, {"name": "adoption", "value": "10223"}, {"name": "morbidly", "value": "9629"}, {"name": "sky", "value": "9104"}, {"name": "SOs", "value": "9034"}, {"name": "husband", "value": "8467"}, {"name": "Target", "value": "8296"}, {"name": "DDC", "value": "8158"}, {"name": "Doesnt", "value": "7974"}, {"name": "safely", "value": "7956"}, {"name": "Thinking", "value": "7862"}, {"name": "DD", "value": "7624"}, {"name": "kitchen", "value": "7287"}, {"name": "bulimic", "value": "7225"}, {"name": "Earth", "value": "7213"}, {"name": "dent", "value": "7029"}, {"name": "complaints", "value": "6875"}, {"name": "agency", "value": "6824"}, {"name": "allergies", "value": "6674"}, {"name": "Costco", "value": "6544"}, {"name": "Devastated", "value": "6423"}, {"name": "drool", "value": "6372"}, {"name": "disgusted", "value": "6354"}, {"name": "control", "value": "6353"}, {"name": "Older", "value": "6125"}, {"name": "Nearly", "value": "5987"}, {"name": "new", "value": "5873"}, {"name": "semen", "value": "5807"}, {"name": "category", "value": "5709"}, {"name": "tray", "value": "5512"}, {"name": "trap", "value": "5511"}, {"name": "happened", "value": "5422"}, {"name": "antidepressants", "value": "5361"}, {"name": "happened", "value": "5316"}, {"name": "crash", "value": "5293"}, {"name": "miscarried", "value": "5234"}, {"name": "happened", "value": "5104"}, {"name": "whiny", "value": "4862"}, {"name": "crawling", "value": "4768"}, {"name": "brushes", "value": "4700"}, {"name": "panic", "value": "4665"}, {"name": "fortunate", "value": "4437"}, {"name": "serial", "value": "4419"}, {"name": "tab", "value": "4354"}, {"name": "tag", "value": "4251"}, {"name": "tad", "value": "4233"}, {"name": "tap", "value": "4148"}, {"name": "slaps", "value": "4140"}, {"name": "annoy", "value": "4128"}, {"name": "penis", "value": "4108"}, {"name": "regularly", "value": "4100"}, {"name": "weeping", "value": "4095"}, {"name": "Robert", "value": "4083"}, {"name": "normally", "value": "4082"}, {"name": "GONNA", "value": "4069"}, {"name": "her", "value": "3997"}, {"name": "waiting", "value": "3989"}, {"name": "failed", "value": "3980"}, {"name": "failed", "value": "3972"}, {"name": "bedrooms", "value": "3971"}, {"name": "bedroom", "value": "3924"}, {"name": "SMH", "value": "3918"}, {"name": "bedroom", "value": "3902"}, {"name": "fights", "value": "3882"}, {"name": "fights", "value": "3879"}, {"name": "tied", "value": "3811"}, {"name": "tits", "value": "3787"}, {"name": "tits", "value": "3726"}, {"name": "recently", "value": "3720"}, {"name": "caller", "value": "3663"}, {"name": "embarassed", "value": "3661"}, {"name": "giggling", "value": "3549"}, {"name": "farm", "value": "3541"}, {"name": "laughed", "value": "3536"}, {"name": "laughed", "value": "3535"}, {"name": "page", "value": "3515"}, {"name": "girlfriend", "value": "3476"}]